README.md
setup.py
cvuts/__init__.py
cvuts/coco_utils.py
cvuts/color_utils.py
cvuts/image_loader.py
cvuts/vis_utils.py
cvuts.egg-info/PKG-INFO
cvuts.egg-info/SOURCES.txt
cvuts.egg-info/dependency_links.txt
cvuts.egg-info/top_level.txt
test/test_image_diff.py
test/test_img_load_time.py
test/test_vis_utils.py