Metadata-Version: 1.0
Name: cvuts
Version: 0.0.1
Summary: this is a tool package for vision-based work, basicaly private XD
Home-page: https://github.com/iHateTa11B0y/cv_utilities
Author: Kuuuurt
Author-email: niu1187203155@gmail.com
License: UNKNOWN
Platform: UNKNOWN
